pyexcel_handsontable/__init__.py
pyexcel_handsontable/handsontable.py
pyexcel_handsontable/templates/components.html
pyexcel_handsontable/templates/css.html
pyexcel_handsontable/templates/embed.html
pyexcel_handsontable/templates/full.html
pyexcel_handsontable/templates/notebook.html
pyexcel_handsontable/templates/registry.json
pyexcel_handsontable/templates/sheet.html
pyexcel_handsontable/templates/pyexcel-handsontable/ZeroClipboard.js
pyexcel_handsontable/templates/pyexcel-handsontable/handsontable.min.css
pyexcel_handsontable/templates/pyexcel-handsontable/handsontable.min.js
pyexcel_handsontable/templates/pyexcel-handsontable/main.js
pyexcel_handsontable/templates/pyexcel-handsontable/moment-2.18.1.min.js
pyexcel_handsontable/templates/pyexcel-handsontable/numbro-1.11.0.min.js
pyexcel_handsontable/templates/pyexcel-handsontable/pikaday-1.5.1.min.js
pyexcel_handsontable-0.0.2.dist-info/DESCRIPTION.rst
pyexcel_handsontable-0.0.2.dist-info/METADATA
pyexcel_handsontable-0.0.2.dist-info/RECORD
pyexcel_handsontable-0.0.2.dist-info/WHEEL
pyexcel_handsontable-0.0.2.dist-info/metadata.json
pyexcel_handsontable-0.0.2.dist-info/top_level.txt
