Metadata-Version: 2.0
Name: pyexcel-handsontable
Version: 0.0.2
Summary: A pyexcel plugin to render data as handsontable in html pages
Home-page: https://github.com/pyexcel-renderers/pyexcel-handsontable
Author: C.W.
Author-email: wangc_2011@hotmail.com
License: New BSD
Download-URL: https://github.com/pyexcel-renderers/pyexcel-handsontable/archive/0.0.2.tar.gz
Keywords: python
Platform: UNKNOWN
Classifier: Topic :: Software Development :: Libraries
Classifier: Programming Language :: Python
Classifier: Intended Audience :: Developers
Classifier: Programming Language :: Python :: 2.6
Classifier: Programming Language :: Python :: 2.7
Classifier: Programming Language :: Python :: 3.3
Classifier: Programming Language :: Python :: 3.4
Classifier: Programming Language :: Python :: 3.5
Classifier: Programming Language :: Python :: 3.6
Classifier: License :: OSI Approved :: BSD License
Requires-Dist: pyexcel (>=0.5.0)
Requires-Dist: jinja2
